MANIFEST.in
README.md
setup.py
src/masonite/qiniu/QiniuServer.py
src/masonite/qiniu/__init__.py
src/masonite/qiniu/configs/qiniu.py
src/masonite/qiniu/providers/QiniuProvider.py
src/masonite/qiniu/providers/__init__.py
src/masonite_qiniu.egg-info/PKG-INFO
src/masonite_qiniu.egg-info/SOURCES.txt
src/masonite_qiniu.egg-info/dependency_links.txt
src/masonite_qiniu.egg-info/requires.txt
src/masonite_qiniu.egg-info/top_level.txt