Metadata-Version: 2.1
Name: masonite-qiniu
Version: 1.0.1
Summary: Qiniu For Masonite
Home-page: https://github.com/puzzle9/masonite-qiniu
Author: puzzle9
Author-email: happypuzzle@126.com
License: MIT
Keywords: qiniu masonite
Platform: UNKNOWN
Classifier: Development Status :: 5 - Production/Stable
Classifier: Intended Audience :: Developers
Classifier: Operating System :: OS Independent
Classifier: License :: OSI Approved :: MIT License
Classifier: Programming Language :: Python :: 3.4
Classifier: Programming Language :: Python :: 3.5
Classifier: Programming Language :: Python :: 3.6
Classifier: Programming Language :: Python :: 3.7
Classifier: Programming Language :: Python :: 3 :: Only
Classifier: Topic :: Software Development :: Libraries
Classifier: Topic :: Utilities
Provides-Extra: test
